dataclass_bakery/__init__.py
dataclass_bakery/baker.py
dataclass_bakery/generators/__init__.py
dataclass_bakery/generators/defaults.py
dataclass_bakery/generators/generators_exceptions.py
dataclass_bakery/generators/random_bool_generator.py
dataclass_bakery/generators/random_complex_generator.py
dataclass_bakery/generators/random_data_class_generator.py
dataclass_bakery/generators/random_date_generator.py
dataclass_bakery/generators/random_datetime_generator.py
dataclass_bakery/generators/random_decimal_generator.py
dataclass_bakery/generators/random_dict_generator.py
dataclass_bakery/generators/random_float_generator.py
dataclass_bakery/generators/random_generator.py
dataclass_bakery/generators/random_int_generator.py
dataclass_bakery/generators/random_list_generator.py
dataclass_bakery/generators/random_option_generator.py
dataclass_bakery/generators/random_path_generator.py
dataclass_bakery/generators/random_range_generator.py
dataclass_bakery/generators/random_set_generator.py
dataclass_bakery/generators/random_str_generator.py
dataclass_bakery/generators/random_tuple_generator.py
dataclass_bakery/generators/random_uuid_generator.py
tests/__init__.py
tests/testing_dataclasses.py
tests/dataclass_bakery/__init__.py
tests/dataclass_bakery/test_baker.py
tests/dataclass_bakery/generators/__init__.py
tests/dataclass_bakery/generators/test_random_bool_generator.py
tests/dataclass_bakery/generators/test_random_complex_generator.py
tests/dataclass_bakery/generators/test_random_data_class_generator.py
tests/dataclass_bakery/generators/test_random_date_generator.py
tests/dataclass_bakery/generators/test_random_datetime_generator.py
tests/dataclass_bakery/generators/test_random_decimal_generator.py
tests/dataclass_bakery/generators/test_random_dict_generator.py
tests/dataclass_bakery/generators/test_random_float_generator.py
tests/dataclass_bakery/generators/test_random_int_generator.py
tests/dataclass_bakery/generators/test_random_list_generator.py
dataclass_bakery-0.0.8.dist-info/LICENSE
dataclass_bakery-0.0.8.dist-info/METADATA
dataclass_bakery-0.0.8.dist-info/WHEEL
dataclass_bakery-0.0.8.dist-info/top_level.txt
dataclass_bakery-0.0.8.dist-info/RECORD
