Metadata-Version: 2.1
Name: dataclass-bakery
Version: 0.0.8
Summary: Dataclass Bakery offers you a smart way to create objects based on dataclasses for testing in Python
Home-page: https://github.com/miguelFLG13/dataclass-bakery
Author: Miguel Jiménez
Author-email: miguelflg13@gmx.com
License: UNKNOWN
Download-URL: https://github.com/miguelFLG13/dataclass-bakery/tarball/0.0.8
Keywords: testing dataclass bakery
Platform: UNKNOWN
Classifier: Programming Language :: Python
Classifier: Programming Language :: Python :: 3
Classifier: Programming Language :: Python :: 3.7
Classifier: Programming Language :: Python :: 3.8
Classifier: Programming Language :: Python :: 3.9
Classifier: Programming Language :: Python :: 3.10
Classifier: Programming Language :: Python :: 3.11
Classifier: Programming Language :: Python :: 3.12
Requires-Python: >=3.7
License-File: LICENSE
